{
  "configVersion": 1,
  "timestamp": 1633422101487,
  "index": "./index.html",
  "assetGroups": [
    {
      "name": "app",
      "installMode": "prefetch",
      "updateMode": "prefetch",
      "cacheQueryOptions": {
        "ignoreVary": true
      },
      "urls": [
        "./121.9c3ebb1897697777128a.js",
        "./222.aba5e0c22738c81ee93a.js",
        "./228.14ea8462a775058c81cc.js",
        "./336.700572a4279f57c6fd44.js",
        "./389.125cbfe54a054958ec07.js",
        "./412.3715b7475f2b344f0fcb.js",
        "./42.e53dccc43804d22d61b7.js",
        "./451.7c9805e02f36dc0b27e1.js",
        "./50.6a962d817c6a02316d8a.js",
        "./559.baa291de45c04cc031f4.js",
        "./592.7d6c9aeb1f74eb8d7090.js",
        "./68.89308714084dd38d3a3d.js",
        "./975.e38a9b037fc14a14046c.js",
        "./987.2d905f9376280c857e4c.js",
        "./favicon.ico",
        "./index.html",
        "./main.d75c9243dd8269d726ec.js",
        "./manifest.webmanifest",
        "./polyfills.880558c9a7448612dc55.js",
        "./runtime.c5330fdefef9747a8c32.js",
        "./styles.0f5b463ded5a9b4eec2e.css"
      ],
      "patterns": []
    },
    {
      "name": "assets",
      "installMode": "lazy",
      "updateMode": "prefetch",
      "cacheQueryOptions": {
        "ignoreVary": true
      },
      "urls": [
        "./Engine-Backoffice.4447ecd55b8a06d35857.ttf",
        "./Engine-Backoffice.8ece9ec0ea90e20a52fc.woff2",
        "./Engine-Backoffice.9cf53d2520daaf07e5db.svg",
        "./Engine-Backoffice.eba34f6d8a439577bafa.woff",
        "./Engine-Backoffice.ec5276ac526f471b16b0.eot",
        "./FiraCode-Bold.4be56996e127ca0cc550.woff2",
        "./FiraCode-Bold.b09eb4c939e990e8f9e8.woff",
        "./FiraCode-Light.52d95ea4712e5a0813df.woff2",
        "./FiraCode-Light.e37fbea8ec98ce1ed3c5.woff",
        "./FiraCode-Medium.eb8dedc4535518d86ddf.woff2",
        "./FiraCode-Medium.edb17cd034ab2bf0c2d4.woff",
        "./FiraCode-Regular.19a2738eed5f65644ea5.woff",
        "./FiraCode-Regular.fb1bb49c43d015b78056.woff2",
        "./FiraCode-SemiBold.19a3cef3cb1f27e6a34c.woff",
        "./FiraCode-SemiBold.f47f1f9dd31e118f14d8.woff2",
        "./FiraCode-VF.145e4ac7976fbd199e74.woff2",
        "./FiraCode-VF.b55b39ac4c8e1fe04870.woff",
        "./MaterialIcons-Regular.4674f8ded773cb03e824.eot",
        "./MaterialIcons-Regular.5e7382c63da0098d634a.ttf",
        "./MaterialIcons-Regular.83bebaf37c09c7e1c3ee.woff",
        "./MaterialIcons-Regular.cff684e59ffb052d72cb.woff2",
        "./Roboto-Black.7f3ed21e03b4eb1c140e.ttf",
        "./Roboto-BlackItalic.adf8927712ad9553f482.ttf",
        "./Roboto-Bold.9630c546d8b557e14b59.ttf",
        "./Roboto-Light.057aa247b66ac02c29b3.ttf",
        "./Roboto-Medium.ea7d3afe129bb3e2ff35.ttf",
        "./Roboto-Regular.d08b3cc873089fdba7fb.ttf",
        "./Young-italic.644b6302cb6e0bc700cf.ttf",
        "./Young.d7bf2462805a7ddc3421.ttf",
        "./assets/404.html",
        "./assets/Young.ttf",
        "./assets/icon/apple-touch-icon-114x114.png",
        "./assets/icon/apple-touch-icon-120x120.png",
        "./assets/icon/apple-touch-icon-144x144.png",
        "./assets/icon/apple-touch-icon-152x152.png",
        "./assets/icon/apple-touch-icon-57x57.png",
        "./assets/icon/apple-touch-icon-60x60.png",
        "./assets/icon/apple-touch-icon-72x72.png",
        "./assets/icon/apple-touch-icon-76x76.png",
        "./assets/icon/code.txt",
        "./assets/icon/favicon-128.png",
        "./assets/icon/favicon-16x16.png",
        "./assets/icon/favicon-196x196.png",
        "./assets/icon/favicon-32x32.png",
        "./assets/icon/favicon-96x96.png",
        "./assets/icon/favicon.ico",
        "./assets/icon/launch.png",
        "./assets/icon/mstile-144x144.png",
        "./assets/icon/mstile-150x150.png",
        "./assets/icon/mstile-310x150.png",
        "./assets/icon/mstile-310x310.png",
        "./assets/icon/mstile-70x70.png",
        "./assets/icons/icon-128x128.png",
        "./assets/icons/icon-144x144.png",
        "./assets/icons/icon-152x152.png",
        "./assets/icons/icon-192x192.png",
        "./assets/icons/icon-384x384.png",
        "./assets/icons/icon-512x512.png",
        "./assets/icons/icon-72x72.png",
        "./assets/icons/icon-96x96.png",
        "./assets/img/logo-inverse.svg",
        "./assets/img/logo.svg",
        "./assets/img/support/chrome-logo.svg",
        "./assets/img/support/edge-logo.svg",
        "./assets/img/support/firefox-logo.svg",
        "./assets/img/support/opera-logo.svg",
        "./assets/img/support/safari-logo.svg",
        "./assets/md5_worker.js",
        "./assets/monaco/vs/base/browser/ui/codicons/codicon/codicon.ttf",
        "./assets/monaco/vs/base/worker/workerMain.js",
        "./assets/monaco/vs/basic-languages/abap/abap.js",
        "./assets/monaco/vs/basic-languages/apex/apex.js",
        "./assets/monaco/vs/basic-languages/azcli/azcli.js",
        "./assets/monaco/vs/basic-languages/bat/bat.js",
        "./assets/monaco/vs/basic-languages/bicep/bicep.js",
        "./assets/monaco/vs/basic-languages/cameligo/cameligo.js",
        "./assets/monaco/vs/basic-languages/clojure/clojure.js",
        "./assets/monaco/vs/basic-languages/coffee/coffee.js",
        "./assets/monaco/vs/basic-languages/cpp/cpp.js",
        "./assets/monaco/vs/basic-languages/csharp/csharp.js",
        "./assets/monaco/vs/basic-languages/csp/csp.js",
        "./assets/monaco/vs/basic-languages/css/css.js",
        "./assets/monaco/vs/basic-languages/dart/dart.js",
        "./assets/monaco/vs/basic-languages/dockerfile/dockerfile.js",
        "./assets/monaco/vs/basic-languages/ecl/ecl.js",
        "./assets/monaco/vs/basic-languages/elixir/elixir.js",
        "./assets/monaco/vs/basic-languages/fsharp/fsharp.js",
        "./assets/monaco/vs/basic-languages/go/go.js",
        "./assets/monaco/vs/basic-languages/graphql/graphql.js",
        "./assets/monaco/vs/basic-languages/handlebars/handlebars.js",
        "./assets/monaco/vs/basic-languages/hcl/hcl.js",
        "./assets/monaco/vs/basic-languages/html/html.js",
        "./assets/monaco/vs/basic-languages/ini/ini.js",
        "./assets/monaco/vs/basic-languages/java/java.js",
        "./assets/monaco/vs/basic-languages/javascript/javascript.js",
        "./assets/monaco/vs/basic-languages/julia/julia.js",
        "./assets/monaco/vs/basic-languages/kotlin/kotlin.js",
        "./assets/monaco/vs/basic-languages/less/less.js",
        "./assets/monaco/vs/basic-languages/lexon/lexon.js",
        "./assets/monaco/vs/basic-languages/liquid/liquid.js",
        "./assets/monaco/vs/basic-languages/lua/lua.js",
        "./assets/monaco/vs/basic-languages/m3/m3.js",
        "./assets/monaco/vs/basic-languages/markdown/markdown.js",
        "./assets/monaco/vs/basic-languages/mips/mips.js",
        "./assets/monaco/vs/basic-languages/msdax/msdax.js",
        "./assets/monaco/vs/basic-languages/mysql/mysql.js",
        "./assets/monaco/vs/basic-languages/objective-c/objective-c.js",
        "./assets/monaco/vs/basic-languages/pascal/pascal.js",
        "./assets/monaco/vs/basic-languages/pascaligo/pascaligo.js",
        "./assets/monaco/vs/basic-languages/perl/perl.js",
        "./assets/monaco/vs/basic-languages/pgsql/pgsql.js",
        "./assets/monaco/vs/basic-languages/php/php.js",
        "./assets/monaco/vs/basic-languages/postiats/postiats.js",
        "./assets/monaco/vs/basic-languages/powerquery/powerquery.js",
        "./assets/monaco/vs/basic-languages/powershell/powershell.js",
        "./assets/monaco/vs/basic-languages/pug/pug.js",
        "./assets/monaco/vs/basic-languages/python/python.js",
        "./assets/monaco/vs/basic-languages/qsharp/qsharp.js",
        "./assets/monaco/vs/basic-languages/r/r.js",
        "./assets/monaco/vs/basic-languages/razor/razor.js",
        "./assets/monaco/vs/basic-languages/redis/redis.js",
        "./assets/monaco/vs/basic-languages/redshift/redshift.js",
        "./assets/monaco/vs/basic-languages/restructuredtext/restructuredtext.js",
        "./assets/monaco/vs/basic-languages/ruby/ruby.js",
        "./assets/monaco/vs/basic-languages/rust/rust.js",
        "./assets/monaco/vs/basic-languages/sb/sb.js",
        "./assets/monaco/vs/basic-languages/scala/scala.js",
        "./assets/monaco/vs/basic-languages/scheme/scheme.js",
        "./assets/monaco/vs/basic-languages/scss/scss.js",
        "./assets/monaco/vs/basic-languages/shell/shell.js",
        "./assets/monaco/vs/basic-languages/solidity/solidity.js",
        "./assets/monaco/vs/basic-languages/sophia/sophia.js",
        "./assets/monaco/vs/basic-languages/sparql/sparql.js",
        "./assets/monaco/vs/basic-languages/sql/sql.js",
        "./assets/monaco/vs/basic-languages/st/st.js",
        "./assets/monaco/vs/basic-languages/swift/swift.js",
        "./assets/monaco/vs/basic-languages/systemverilog/systemverilog.js",
        "./assets/monaco/vs/basic-languages/tcl/tcl.js",
        "./assets/monaco/vs/basic-languages/twig/twig.js",
        "./assets/monaco/vs/basic-languages/typescript/typescript.js",
        "./assets/monaco/vs/basic-languages/vb/vb.js",
        "./assets/monaco/vs/basic-languages/xml/xml.js",
        "./assets/monaco/vs/basic-languages/yaml/yaml.js",
        "./assets/monaco/vs/editor/editor.main.css",
        "./assets/monaco/vs/editor/editor.main.js",
        "./assets/monaco/vs/editor/editor.main.nls.de.js",
        "./assets/monaco/vs/editor/editor.main.nls.es.js",
        "./assets/monaco/vs/editor/editor.main.nls.fr.js",
        "./assets/monaco/vs/editor/editor.main.nls.it.js",
        "./assets/monaco/vs/editor/editor.main.nls.ja.js",
        "./assets/monaco/vs/editor/editor.main.nls.js",
        "./assets/monaco/vs/editor/editor.main.nls.ko.js",
        "./assets/monaco/vs/editor/editor.main.nls.ru.js",
        "./assets/monaco/vs/editor/editor.main.nls.zh-cn.js",
        "./assets/monaco/vs/editor/editor.main.nls.zh-tw.js",
        "./assets/monaco/vs/language/css/cssMode.js",
        "./assets/monaco/vs/language/css/cssWorker.js",
        "./assets/monaco/vs/language/html/htmlMode.js",
        "./assets/monaco/vs/language/html/htmlWorker.js",
        "./assets/monaco/vs/language/json/jsonMode.js",
        "./assets/monaco/vs/language/json/jsonWorker.js",
        "./assets/monaco/vs/language/typescript/tsMode.js",
        "./assets/monaco/vs/language/typescript/tsWorker.js",
        "./assets/monaco/vs/loader.js",
        "./assets/not-supported.html"
      ],
      "patterns": []
    }
  ],
  "dataGroups": [],
  "hashTable": {
    "./121.9c3ebb1897697777128a.js": "0d83a259257b67fffd352cebff10e178759e437d",
    "./222.aba5e0c22738c81ee93a.js": "48a62b2db32f29743aed5db38155bacace3466cc",
    "./228.14ea8462a775058c81cc.js": "d683199ee24dd8081b45d71323601cb8423d46e8",
    "./336.700572a4279f57c6fd44.js": "e4671962a7b3cfacd9027e2216cb1c9e6fbeab55",
    "./389.125cbfe54a054958ec07.js": "903d1b8da2fdb01afb636aa93f47495716f0d3fb",
    "./412.3715b7475f2b344f0fcb.js": "ee68af24afa95d0cad7738efa6debe6049e1893a",
    "./42.e53dccc43804d22d61b7.js": "fe2aa2dfc78a85b8316e4ce70a34da4150daf2c6",
    "./451.7c9805e02f36dc0b27e1.js": "9ceccc0d15e38a78c50f2476ad546571f57c2910",
    "./50.6a962d817c6a02316d8a.js": "daf569345ccacf00c07fcf7e86409e4a09681ff3",
    "./559.baa291de45c04cc031f4.js": "6deeb25833bdabea453532d2f14f1747703615c9",
    "./592.7d6c9aeb1f74eb8d7090.js": "2ea536b18886d6d768f31a898b613323928117d3",
    "./68.89308714084dd38d3a3d.js": "97fdb2265901ca995e65d6422b345192f2bdc291",
    "./975.e38a9b037fc14a14046c.js": "15d68b6194b57a337092b89c84d7db3241e701a0",
    "./987.2d905f9376280c857e4c.js": "16885844f95d9e5fcd29c85659da76204de5fb33",
    "./Engine-Backoffice.4447ecd55b8a06d35857.ttf": "12db162ab2864f8810fce9ad115892ca88208eff",
    "./Engine-Backoffice.8ece9ec0ea90e20a52fc.woff2": "c06e3d4eeffcd88bb80e3b5c6aec8e005e4add8f",
    "./Engine-Backoffice.9cf53d2520daaf07e5db.svg": "22d8f86e4073b65ba57722589fc850bc4330f76d",
    "./Engine-Backoffice.eba34f6d8a439577bafa.woff": "038c9fe08e640422fcbda75a73fee936a3442534",
    "./Engine-Backoffice.ec5276ac526f471b16b0.eot": "984c2d44f1c4f2c57ffbb704d61762e104658cbd",
    "./FiraCode-Bold.4be56996e127ca0cc550.woff2": "b5e83d62a6acd16c8ee0b3964075473bd5c62942",
    "./FiraCode-Bold.b09eb4c939e990e8f9e8.woff": "8600483fb61d0590ded31ac67b0cba2a2ff9c113",
    "./FiraCode-Light.52d95ea4712e5a0813df.woff2": "03bb02009e0ca7d65cb14f98c56c29962ab38d19",
    "./FiraCode-Light.e37fbea8ec98ce1ed3c5.woff": "daeca8d872a7bd7374a2b8d371998f215e839511",
    "./FiraCode-Medium.eb8dedc4535518d86ddf.woff2": "beac20f69c3e534daea6f42e217d5b7d5186177d",
    "./FiraCode-Medium.edb17cd034ab2bf0c2d4.woff": "23007ae82fd73824a8a0c299f496ad483b370330",
    "./FiraCode-Regular.19a2738eed5f65644ea5.woff": "91ce58063a372746cbdf67e02b9cbf714a48fa60",
    "./FiraCode-Regular.fb1bb49c43d015b78056.woff2": "2ba83ee2f19a2bf0fb43cee5bba56576269bfdad",
    "./FiraCode-SemiBold.19a3cef3cb1f27e6a34c.woff": "7a53442a2dd8296587babe4fb8af6188f2f9e633",
    "./FiraCode-SemiBold.f47f1f9dd31e118f14d8.woff2": "bf1e1e02f780e4f5cb7c7911ffe161146f4fa9dc",
    "./FiraCode-VF.145e4ac7976fbd199e74.woff2": "3efb2bfee151a2226d93ff2af41187e7c8fe098c",
    "./FiraCode-VF.b55b39ac4c8e1fe04870.woff": "d6a89274ec6b3d14996efaeef64d70d9b473fde7",
    "./MaterialIcons-Regular.4674f8ded773cb03e824.eot": "26fb8cecb5512223277b4d290a24492a0f09ede1",
    "./MaterialIcons-Regular.5e7382c63da0098d634a.ttf": "fc05de31234e0090f7ddc28ce1b23af4026cb1da",
    "./MaterialIcons-Regular.83bebaf37c09c7e1c3ee.woff": "c6c953c2ccb2ca9abb21db8dbf473b5a435f0082",
    "./MaterialIcons-Regular.cff684e59ffb052d72cb.woff2": "09963592e8c953cc7e14e3fb0a5b05d5042e8435",
    "./Roboto-Black.7f3ed21e03b4eb1c140e.ttf": "771b45f0ceb2a752cd0d705187468e6993fd0fb9",
    "./Roboto-BlackItalic.adf8927712ad9553f482.ttf": "6c8acc36bbdf17bcd6a33756aa42e2557bb3f805",
    "./Roboto-Bold.9630c546d8b557e14b59.ttf": "0a1793926e2ee724cf2ff3fc7adc745348659f82",
    "./Roboto-Light.057aa247b66ac02c29b3.ttf": "2e3148d213b15328ebebba14e828fb3bf79634ee",
    "./Roboto-Medium.ea7d3afe129bb3e2ff35.ttf": "08bab5b1ab478e8af2279b613d3a32636b85cc65",
    "./Roboto-Regular.d08b3cc873089fdba7fb.ttf": "1d1d41fcadc571decb6444211b7993b99ce926e2",
    "./Young-italic.644b6302cb6e0bc700cf.ttf": "fed2dfff32fac3ecd4a7b2ef62bf32058fefa26d",
    "./Young.d7bf2462805a7ddc3421.ttf": "5a10260620ffe874fced9856c58a50d888013047",
    "./assets/404.html": "d863aa310ef1916de60bb0984af4f325fe391c43",
    "./assets/Young.ttf": "5a10260620ffe874fced9856c58a50d888013047",
    "./assets/icon/apple-touch-icon-114x114.png": "3f7b911bc4bc549d056a231f31d96a523b63ecd2",
    "./assets/icon/apple-touch-icon-120x120.png": "48296b5b069763dea291bf89261c0e676f101427",
    "./assets/icon/apple-touch-icon-144x144.png": "dc1274b2e6766c8803bd0c95f56a70aee5e24a83",
    "./assets/icon/apple-touch-icon-152x152.png": "25bfc09816edca1f7097cb4ec96d8a5f61bec51b",
    "./assets/icon/apple-touch-icon-57x57.png": "64d3b5778558b27fc3f6b75af2f94cedddffbbdd",
    "./assets/icon/apple-touch-icon-60x60.png": "b8d10f16add9964882ae5ed0d022aabe4b88b662",
    "./assets/icon/apple-touch-icon-72x72.png": "4ebd11357aa4e78bc6a62ef2ee3fcd23b4116693",
    "./assets/icon/apple-touch-icon-76x76.png": "1c21963d6c8d9a1ed9c233443c0935874d53db38",
    "./assets/icon/code.txt": "af070b5ca0c51ff9b7eb32e5340c3d2641aa3ad9",
    "./assets/icon/favicon-128.png": "5b57bc8a2902765c713be971b37cb19b4ba2ce7a",
    "./assets/icon/favicon-16x16.png": "817a291fada05f5420bbf41819f9c94b84499804",
    "./assets/icon/favicon-196x196.png": "85607c81fd5ac6a96685a25f0125edbcc6188cf2",
    "./assets/icon/favicon-32x32.png": "05ec9a4104c7ce1eb67a6c392f09559300a8cbcf",
    "./assets/icon/favicon-96x96.png": "90dda4b2739159c7f8610e6330d077e03bae9b43",
    "./assets/icon/favicon.ico": "89efb1d87741fe2bfa685ec59bb4b547a295667c",
    "./assets/icon/launch.png": "487125d215627a5a87b2c8a8fe546e21c6289be0",
    "./assets/icon/mstile-144x144.png": "dc1274b2e6766c8803bd0c95f56a70aee5e24a83",
    "./assets/icon/mstile-150x150.png": "84f5699eb440e886e76a182ea7a172b88f5b3efc",
    "./assets/icon/mstile-310x150.png": "932d8a48942e0be36d56807361779eb554371318",
    "./assets/icon/mstile-310x310.png": "f6e8f3f30f104a05818067a04b34abce77b6d495",
    "./assets/icon/mstile-70x70.png": "5b57bc8a2902765c713be971b37cb19b4ba2ce7a",
    "./assets/icons/icon-128x128.png": "dae3b6ed49bdaf4327b92531d4b5b4a5d30c7532",
    "./assets/icons/icon-144x144.png": "b0bd89982e08f9bd2b642928f5391915b74799a7",
    "./assets/icons/icon-152x152.png": "7479a9477815dfd9668d60f8b3b2fba709b91310",
    "./assets/icons/icon-192x192.png": "1abd80d431a237a853ce38147d8c63752f10933b",
    "./assets/icons/icon-384x384.png": "329749cd6393768d3131ed6304c136b1ca05f2fd",
    "./assets/icons/icon-512x512.png": "559d9c4318b45a1f2b10596bbb4c960fe521dbcc",
    "./assets/icons/icon-72x72.png": "c457e56089a36952cd67156f9996bc4ce54a5ed9",
    "./assets/icons/icon-96x96.png": "3914125a4b445bf111c5627875fc190f560daa41",
    "./assets/img/logo-inverse.svg": "34a90da886a635b6945716d5499d117d35ca4d23",
    "./assets/img/logo.svg": "7cab49a95f17af958ae8b7376717730f77eb5e18",
    "./assets/img/support/chrome-logo.svg": "265fb92c1ab3d68ac7fc58c70c6a42e77569288f",
    "./assets/img/support/edge-logo.svg": "28d8691fd6c19223a3d99dd8732416d32a82d496",
    "./assets/img/support/firefox-logo.svg": "5d92cf1198425c8696bbd4c4c79f7ee029a207b9",
    "./assets/img/support/opera-logo.svg": "23f8e25409598ac843eefe81ea3c09b4f460844d",
    "./assets/img/support/safari-logo.svg": "1c510b0c330f84f6662351e4a0abd7fb8af2f678",
    "./assets/md5_worker.js": "6cb4b4f68e8c9933cb9052e488a348379e05d82d",
    "./assets/monaco/vs/base/browser/ui/codicons/codicon/codicon.ttf": "b38914556e28324f49d744167982ce5990bc8d74",
    "./assets/monaco/vs/base/worker/workerMain.js": "bd60f48bb78d9856ddd5d6f7fa5a3c00ca99002c",
    "./assets/monaco/vs/basic-languages/abap/abap.js": "51ad6d83128ab5b9d342b170288d3354a18708b3",
    "./assets/monaco/vs/basic-languages/apex/apex.js": "30ec55cd11307124dd18dfc401f7c94528fc6774",
    "./assets/monaco/vs/basic-languages/azcli/azcli.js": "99e7f605776042a92e85f19e73b8c6b2b0d1104a",
    "./assets/monaco/vs/basic-languages/bat/bat.js": "f55b67c83aa04b7ca605c213d8b1631f862c59f2",
    "./assets/monaco/vs/basic-languages/bicep/bicep.js": "3edd2ac9ee80a019b43080bd45bbe8e5aec23b8e",
    "./assets/monaco/vs/basic-languages/cameligo/cameligo.js": "6455dee2bad899c4ef83a3bf5cf10b3638d8d673",
    "./assets/monaco/vs/basic-languages/clojure/clojure.js": "b5c3e32dc9ccdf6d4dd81aac9e9b1769a1841023",
    "./assets/monaco/vs/basic-languages/coffee/coffee.js": "5287c5eebea6c30dbf84898570e756a9b1ef4087",
    "./assets/monaco/vs/basic-languages/cpp/cpp.js": "bcefd9d0a4d188dea83a85aee855823242484051",
    "./assets/monaco/vs/basic-languages/csharp/csharp.js": "4ea0971478c3b938c20218c6abb1b5d667989762",
    "./assets/monaco/vs/basic-languages/csp/csp.js": "32222382feeca3cbe82428ec743338baa880c0a4",
    "./assets/monaco/vs/basic-languages/css/css.js": "483554ff8bc7fdf9e897fe7130649a4c4489b1b2",
    "./assets/monaco/vs/basic-languages/dart/dart.js": "2a4bea53ea3c196bc2d06b110e4db29b2d237503",
    "./assets/monaco/vs/basic-languages/dockerfile/dockerfile.js": "a88f116ba4a4b5912129def99c7a23cbbd1d91c0",
    "./assets/monaco/vs/basic-languages/ecl/ecl.js": "069c6e17bcd8ef29098609139737ba74d93f0c07",
    "./assets/monaco/vs/basic-languages/elixir/elixir.js": "8aa2b44e2b52c1dbe1b8d8018c901da99a84b040",
    "./assets/monaco/vs/basic-languages/fsharp/fsharp.js": "be275515c1ec1d0d2966abd255dbcb4e56bb5d5a",
    "./assets/monaco/vs/basic-languages/go/go.js": "52672db8f68128169e478afa2e62b86b5ecd5da4",
    "./assets/monaco/vs/basic-languages/graphql/graphql.js": "a180bc20bcb1388cad3f25ce262380abd58011ee",
    "./assets/monaco/vs/basic-languages/handlebars/handlebars.js": "5abb55c5823a21859e0ae9f3255d98fe5d93b43c",
    "./assets/monaco/vs/basic-languages/hcl/hcl.js": "d326ea078d1af2f9aa2dd2757d6c241924a80a68",
    "./assets/monaco/vs/basic-languages/html/html.js": "43913f73da60a6593b446f24470e6f642b59c23b",
    "./assets/monaco/vs/basic-languages/ini/ini.js": "879ce72309bf0f8c09dc8efc4205be713c5fe63d",
    "./assets/monaco/vs/basic-languages/java/java.js": "eba16e61c9508f304f0a6d32f2530a081f9f71d0",
    "./assets/monaco/vs/basic-languages/javascript/javascript.js": "aef606b2b6ba1a80e1b1be145469fb83d90bb463",
    "./assets/monaco/vs/basic-languages/julia/julia.js": "8573249afe4643b7285b4ea72358572a17428543",
    "./assets/monaco/vs/basic-languages/kotlin/kotlin.js": "6e24f7bf064cb789eb7163711f7a7a730522dcd6",
    "./assets/monaco/vs/basic-languages/less/less.js": "e0a881566a8b5aea0d54fa1990cd2f436ce44513",
    "./assets/monaco/vs/basic-languages/lexon/lexon.js": "ea6e2934da7a5e8a772da75b013bb069de102b75",
    "./assets/monaco/vs/basic-languages/liquid/liquid.js": "2c3292d6229fc8b44350e8c8c9b3d2163d8edee4",
    "./assets/monaco/vs/basic-languages/lua/lua.js": "f65622fd6321fd129b6e84cb11fc8c23c577dd53",
    "./assets/monaco/vs/basic-languages/m3/m3.js": "db60ca157440d3e049ccdb58861d493ffa65f385",
    "./assets/monaco/vs/basic-languages/markdown/markdown.js": "2ed682e0dd17e5dc39617d400e9277b7cf68ccc6",
    "./assets/monaco/vs/basic-languages/mips/mips.js": "d68caa1b9e2115736467b5ea10db4be57dd5e0c1",
    "./assets/monaco/vs/basic-languages/msdax/msdax.js": "77e0a0f3136bae617f0b80f23417160c544cf60c",
    "./assets/monaco/vs/basic-languages/mysql/mysql.js": "7f5fa2fafd75c043cffd5661953ae29d29792e6c",
    "./assets/monaco/vs/basic-languages/objective-c/objective-c.js": "945476b1534287343f1fcb2ff8462ca1fd8f29ef",
    "./assets/monaco/vs/basic-languages/pascal/pascal.js": "06e7ac8a07f4a684535d98261633349c970e0734",
    "./assets/monaco/vs/basic-languages/pascaligo/pascaligo.js": "9d5c9fc61d9ac117bc6a2ff4feb6f8052d768b34",
    "./assets/monaco/vs/basic-languages/perl/perl.js": "5bde96cb81e70712e66ae8ce5a6f31c843c5a356",
    "./assets/monaco/vs/basic-languages/pgsql/pgsql.js": "910c41822f0887929832b60b6924dff356d3958b",
    "./assets/monaco/vs/basic-languages/php/php.js": "2b0f101e0d5f247c47cc72eede8e825d6e8aa9fc",
    "./assets/monaco/vs/basic-languages/postiats/postiats.js": "5848fa270407daa272bf8accc4494a7ac3f6963a",
    "./assets/monaco/vs/basic-languages/powerquery/powerquery.js": "e5ec3080dcbe86b287eac474365c95ab93540916",
    "./assets/monaco/vs/basic-languages/powershell/powershell.js": "0245c49b9847585c911bb14a158bed0c723ec1e7",
    "./assets/monaco/vs/basic-languages/pug/pug.js": "233cbf14317621dd6a604da9a34085a7c2a414fd",
    "./assets/monaco/vs/basic-languages/python/python.js": "8aafea0a65bb5434f2effb908ba6a0313b5f2aba",
    "./assets/monaco/vs/basic-languages/qsharp/qsharp.js": "3e173f883b0bf6b80916ef662d98d64130d36a72",
    "./assets/monaco/vs/basic-languages/r/r.js": "f51ea05e9be6a5d9acdef7d6ee06ffb95bb88323",
    "./assets/monaco/vs/basic-languages/razor/razor.js": "1635eb71bd23a6b29f7145002f66479eda3246b9",
    "./assets/monaco/vs/basic-languages/redis/redis.js": "5d8fdf331c7a95fbcc0cf11df9a0054e3cef5473",
    "./assets/monaco/vs/basic-languages/redshift/redshift.js": "f71946e3e03616f9dc36aedd52cdc51a95f94d2d",
    "./assets/monaco/vs/basic-languages/restructuredtext/restructuredtext.js": "b39f867942d35b7596ee3ce78be360e22489a5ae",
    "./assets/monaco/vs/basic-languages/ruby/ruby.js": "eb241c79ae1f9bb621061e2f756ecece47c2ba71",
    "./assets/monaco/vs/basic-languages/rust/rust.js": "0ae8d4cc019231d54f5a3466ef21301a18ca4a31",
    "./assets/monaco/vs/basic-languages/sb/sb.js": "82ed72c4669a578cd1150846894dfcdcf5dd00a7",
    "./assets/monaco/vs/basic-languages/scala/scala.js": "80b49620e9487096976fe1a19fcae469cdc152dd",
    "./assets/monaco/vs/basic-languages/scheme/scheme.js": "89ee013482c975d54c88171428ee5c13b61e7019",
    "./assets/monaco/vs/basic-languages/scss/scss.js": "6da7d695de664ff3c9a2a8afa7d4a0040c7b8cc5",
    "./assets/monaco/vs/basic-languages/shell/shell.js": "d3c50f71a48682cb8e01e0d7e1a498a47445faca",
    "./assets/monaco/vs/basic-languages/solidity/solidity.js": "c819c9229f0a12fcf568544a638992d9774a9935",
    "./assets/monaco/vs/basic-languages/sophia/sophia.js": "f9242ee5d2d67d7fae312653775a1996141c1432",
    "./assets/monaco/vs/basic-languages/sparql/sparql.js": "545d376b02936554031560b7000e6e27d3586db7",
    "./assets/monaco/vs/basic-languages/sql/sql.js": "1bc039f3858222101773af8f8704d9ac0d43c8fc",
    "./assets/monaco/vs/basic-languages/st/st.js": "8084202581dcd8b40caeae730e258ec50995e761",
    "./assets/monaco/vs/basic-languages/swift/swift.js": "9ee51cfa9c83a46ea07c173e15bf5640db19245c",
    "./assets/monaco/vs/basic-languages/systemverilog/systemverilog.js": "d06b398b37b597a97c67d2878298d07c653bb942",
    "./assets/monaco/vs/basic-languages/tcl/tcl.js": "bc152b4d7ad4a7772911ecf03e84c263d68c7ea9",
    "./assets/monaco/vs/basic-languages/twig/twig.js": "3e4b4738f3ba9ce5374e2f4d9095bde140fd55a8",
    "./assets/monaco/vs/basic-languages/typescript/typescript.js": "620fe42b6ef1c807a26cbd453029c9bc7156b97a",
    "./assets/monaco/vs/basic-languages/vb/vb.js": "9822a289ede2437f31edc88a42b09da828eb178a",
    "./assets/monaco/vs/basic-languages/xml/xml.js": "ec6d382584a7c483de06f281c69d28f92ad24093",
    "./assets/monaco/vs/basic-languages/yaml/yaml.js": "5a20dc725abbb19eb6c7d15ed1b275c3394c1ac6",
    "./assets/monaco/vs/editor/editor.main.css": "7d044a63be7becbee99fc03b91fdc847fc708a25",
    "./assets/monaco/vs/editor/editor.main.js": "fff89505b5cbbcec8bb28672ef7797a7b5afbdf1",
    "./assets/monaco/vs/editor/editor.main.nls.de.js": "b663ddb5dcbf348ca25e6a74240fdfa073a8127e",
    "./assets/monaco/vs/editor/editor.main.nls.es.js": "9cfcb676d74dbc2f32c1e777348d7c3b89e1cf35",
    "./assets/monaco/vs/editor/editor.main.nls.fr.js": "38e33df1e65648d957dffc83d205359485aa8b01",
    "./assets/monaco/vs/editor/editor.main.nls.it.js": "864fa493546f2171096741aef4f2a84ec2096b9d",
    "./assets/monaco/vs/editor/editor.main.nls.ja.js": "2e3e39edf5c7e54bdd6c170cc678d2ad47d9fa91",
    "./assets/monaco/vs/editor/editor.main.nls.js": "c6ae32a44585725d8aceb63f3bb44f1918efaffa",
    "./assets/monaco/vs/editor/editor.main.nls.ko.js": "cef502ef62d75dee59272d0ec5fae2c639a05800",
    "./assets/monaco/vs/editor/editor.main.nls.ru.js": "0f3f7ac09d2003b3d210ff57517ac1acfeaad511",
    "./assets/monaco/vs/editor/editor.main.nls.zh-cn.js": "a6b41ee1cc2341034b1bf67cb9706a129a09116e",
    "./assets/monaco/vs/editor/editor.main.nls.zh-tw.js": "19189d432624dde36d8093756216e34099067c4c",
    "./assets/monaco/vs/language/css/cssMode.js": "59951d38cf37788ff134a38526828fda5d2a846b",
    "./assets/monaco/vs/language/css/cssWorker.js": "f2f43be71d55b6528c4405d0d4344dc40aa0295f",
    "./assets/monaco/vs/language/html/htmlMode.js": "bc3a71d3dfa2ff0585acc3f6a0313aec121ae827",
    "./assets/monaco/vs/language/html/htmlWorker.js": "64739fe20487b477944d68375e973d33400f06c7",
    "./assets/monaco/vs/language/json/jsonMode.js": "384373fbeec0e6fbf29481475ddb045125d31a82",
    "./assets/monaco/vs/language/json/jsonWorker.js": "fda681558b3d1ca184a0d5f53e8a4e9dfda42e70",
    "./assets/monaco/vs/language/typescript/tsMode.js": "8e996a5654ac75458c9695441915d5d696c05c3a",
    "./assets/monaco/vs/language/typescript/tsWorker.js": "93de4b0bbf955f63442e209e8633956bba870501",
    "./assets/monaco/vs/loader.js": "97d90c9c21ef8e514fec0fe2466a3b402ac4c747",
    "./assets/not-supported.html": "95103c6d901e99e32b94b716edc18f85004d7c87",
    "./favicon.ico": "fdc860283294c177c4935459507f4976ac8d7219",
    "./index.html": "742c06b1d7b3cfdcd8ed2585ea596adfb3835769",
    "./main.d75c9243dd8269d726ec.js": "276e80f82e4ff7ac23a30f8a5c40f1ce4847871c",
    "./manifest.webmanifest": "df9f9536bf7b49b5e3075980c5fa159c81b50b28",
    "./polyfills.880558c9a7448612dc55.js": "2b9bf42c4555217ed918c522e52c19c67e27de3f",
    "./runtime.c5330fdefef9747a8c32.js": "8e1c4a30c9d01785659219477525e9626396ed3d",
    "./styles.0f5b463ded5a9b4eec2e.css": "98b677cb16e46eb25f427676dda0233fe7a0e425"
  },
  "navigationUrls": [
    {
      "positive": true,
      "regex": "^\\/.*$"
    },
    {
      "positive": false,
      "regex": "^\\/(?:.+\\/)?[^/]*\\.[^/]*$"
    },
    {
      "positive": false,
      "regex": "^\\/(?:.+\\/)?[^/]*__[^/]*$"
    },
    {
      "positive": false,
      "regex": "^\\/(?:.+\\/)?[^/]*__[^/]*\\/.*$"
    }
  ],
  "navigationRequestStrategy": "performance"
}